240968332 (Backup)/DISL (Backup)/lab7/dff_async_reset.v
module dff_async_reset (
    input clk,       // Clock input
    input reset,     // Asynchronous active high reset
    input d,         // Data input
    output reg q     // Output
);

always @(posedge clk or posedge reset) begin
    if (reset)
        q <= 1'b0;
    else
        q <= d;
end

endmodule

240968332 (Backup)/DISL (Backup)/lab7/tb_dff_async_reset.v
`timescale 1ns / 1ps

module tb_dff_async_reset;
reg clk;
reg reset;
reg d;
wire q;
dff_async_reset uut (
    .clk(clk),
    .reset(reset),
    .d(d),
    .q(q)
);

initial begin
    clk = 0;
    forever #5 clk = ~clk;
end
initial begin
    $dumpfile("dff_async_reset.vcd"); 
    $dumpvars(0, tb_dff_async_reset); 
end
initial begin
    $display("Time\tReset\tD\tQ");
    $monitor("%g\t%b\t%b\t%b", $time, reset, d, q);
    reset = 0; d = 0; #10;
    reset = 1; #10;
    reset = 0; d = 1; #10;
    d = 0; #10;
    reset = 1; #5;
    reset = 0; #5;
    d = 1; #10;

    $finish;
end

endmodule

240968332 (Backup)/DISL (Backup)/lab7/dff_async_reset.vcd
$date
	Thu Sep 25 14:35:02 2025
$end
$version
	Icarus Verilog
$end
$timescale
	1ps
$end
$scope module tb_dff_async_reset $end
$var wire 1 ! q $end
$var reg 1 " clk $end
$var reg 1 # d $end
$var reg 1 $ reset $end
$scope module uut $end
$var wire 1 " clk $end
$var wire 1 # d $end
$var wire 1 $ reset $end
$var reg 1 ! q $end
$upscope $end
$upscope $end
$enddefinitions $end
#0
$dumpvars
0$
0#
0"
x!
$end
#5000
0!
1"
#10000
0"
1$
#15000
1"
#20000
0"
1#
0$
#25000
1!
1"
#30000
0"
0#
#35000
0!
1"
#40000
0"
1$
#45000
1"
0$
#50000
0"
1#
#55000
1!
1"
