240968332 (Backup)/DISL (Backup)/lab7/t_ff_async_reset.v
module t_ff_async_reset (
    input wire clk,     
    input wire reset_n, 
    input wire t,       
    output reg q        
);

always @(negedge clk or negedge reset_n) begin
    if (!reset_n)
        q <= 1'b0;       
    else if (t)
        q <= ~q;         
end

endmodule

240968332 (Backup)/DISL (Backup)/lab7/tb_t_ff_async_reset.v
`timescale 1ns / 1ps
module tb_t_ff_async_reset;
reg clk;
reg reset_n;
reg t;
wire q;
t_ff_async_reset uut (
    .clk(clk),
    .reset_n(reset_n),
    .t(t),
    .q(q)
);
initial begin
    clk = 1;
    forever #5 clk = ~clk; 
end
initial begin
    $dumpfile("t_ff_async_reset.vcd");
    $dumpvars(0, tb_t_ff_async_reset);
end
initial begin
    $display("Time\tReset_n\tT\tQ");
    $monitor("%g\t%b\t%b\t%b", $time, reset_n, t, q);
    reset_n = 1; t = 0; #10;
    reset_n = 0; #10;
    reset_n = 1; t = 1; #10;
    t = 0; #10;
    t = 1; #10;
    reset_n = 0; #2; reset_n = 1; #8;

    $finish;
end

endmodule

240968332 (Backup)/DISL (Backup)/lab7/t_ff_async_reset.vcd
$date
	Thu Sep 25 14:43:26 2025
$end
$version
	Icarus Verilog
$end
$timescale
	1ps
$end
$scope module tb_t_ff_async_reset $end
$var wire 1 ! q $end
$var reg 1 " clk $end
$var reg 1 # reset_n $end
$var reg 1 $ t $end
$scope module uut $end
$var wire 1 " clk $end
$var wire 1 # reset_n $end
$var wire 1 $ t $end
$var reg 1 ! q $end
$upscope $end
$upscope $end
$enddefinitions $end
#0
$dumpvars
0$
1#
1"
x!
$end
#5000
0"
#10000
0!
1"
0#
#15000
0"
#20000
1"
1$
1#
#25000
1!
0"
#30000
1"
0$
#35000
0"
#40000
1"
1$
#45000
0!
0"
#50000
1"
0#
#52000
1#
#55000
1!
0"
