240968332 (Backup)/DISL (Backup)/lab6/decoder3to8.v
module decoder2to4 (
    input en,
    input [1:0] a,
    output reg [3:0] y
);

always @(*) begin
    if (en) begin
        if (a == 2'b00)
            y = 4'b0001;
        else if (a == 2'b01)
            y = 4'b0010;
        else if (a == 2'b10)
            y = 4'b0100;
        else if (a == 2'b11)
            y = 4'b1000;
        else
            y = 4'b0000;  // optional default
    end else begin
        y = 4'b0000;  // Outputs are 0 when not enabled
    end
end

endmodule

module decoder3to8 (
    input en,
    input [2:0] a,
    output [7:0] y
);

wire [3:0] y0, y1;

// Instantiate lower 2-to-4 decoder (when a[2] = 0)
decoder2to4 d0 (
    .en(en & ~a[2]),
    .a(a[1:0]),
    .y(y0)
);

// Instantiate upper 2-to-4 decoder (when a[2] = 1)
decoder2to4 d1 (
    .en(en & a[2]),
    .a(a[1:0]),
    .y(y1)
);

// Combine outputs
assign y = {y1, y0};  // y[7:4] from d1, y[3:0] from d0

endmodule

240968332 (Backup)/DISL (Backup)/lab6/tb_decoder3to8.v
`timescale 1ns / 1ps

module tb_decoder3to8;

    reg en;
    reg [2:0] a;
    wire [7:0] y;

    // Instantiate the Unit Under Test (UUT)
    decoder3to8 uut (
        .en(en),
        .a(a),
        .y(y)
    );

    integer i;

    initial begin
        // Dumpfile and dumpvars for waveform viewing
        $dumpfile("decoder3to8_tb.vcd");  // Output VCD file
        $dumpvars(0, tb_decoder3to8);     // Dump everything in this module

        $display("Time\t en a[2:0] | y[7:0]");
        $display("--------------------------------");

        // Test when enable is low — output should be 0
        en = 0;
        a = 3'b000;
        #10 $display("%0t\t %b  %b | %b", $time, en, a, y);

        // Test all input combinations when enable is high
        en = 1;
        for (i = 0; i < 8; i = i + 1) begin
            a = i[2:0];
            #10 $display("%0t\t %b  %b | %b", $time, en, a, y);
        end

        // Disable again
        en = 0;
        a = 3'b101;
        #10 $display("%0t\t %b  %b | %b", $time, en, a, y);

        $finish;
    end

endmodule

240968332 (Backup)/DISL (Backup)/lab6/decoder3to8_tb.vcd
$date
	Thu Sep 11 14:14:48 2025
$end
$version
	Icarus Verilog
$end
$timescale
	1ps
$end
$scope module tb_decoder3to8 $end
$var wire 8 ! y [7:0] $end
$var reg 3 " a [2:0] $end
$var reg 1 # en $end
$var integer 32 $ i [31:0] $end
$scope module uut $end
$var wire 3 % a [2:0] $end
$var wire 1 # en $end
$var wire 4 & y1 [3:0] $end
$var wire 4 ' y0 [3:0] $end
$var wire 8 ( y [7:0] $end
$scope module d0 $end
$var wire 2 ) a [1:0] $end
$var wire 1 * en $end
$var reg 4 + y [3:0] $end
$upscope $end
$scope module d1 $end
$var wire 2 , a [1:0] $end
$var wire 1 - en $end
$var reg 4 . y [3:0] $end
$upscope $end
$upscope $end
$upscope $end
$enddefinitions $end
#0
$dumpvars
b0 .
0-
b0 ,
b0 +
0*
b0 )
b0 (
b0 '
b0 &
b0 %
bx $
0#
b0 "
b0 !
$end
#10000
b1 !
b1 (
b1 '
b1 +
1*
b0 $
1#
#20000
b10 !
b10 (
b10 '
b10 +
b1 )
b1 ,
b1 "
b1 %
b1 $
#30000
b100 !
b100 (
b100 '
b100 +
b10 )
b10 ,
b10 "
b10 %
b10 $
#40000
b1000 !
b1000 (
b1000 '
b1000 +
b11 )
b11 ,
b11 "
b11 %
b11 $
#50000
0*
b1 &
b1 .
b10000 !
b10000 (
b0 '
b0 +
1-
b0 )
b0 ,
b100 "
b100 %
b100 $
#60000
b100000 !
b100000 (
b10 &
b10 .
b1 )
b1 ,
b101 "
b101 %
b101 $
#70000
b1000000 !
b1000000 (
b100 &
b100 .
b10 )
b10 ,
b110 "
b110 %
b110 $
#80000
b10000000 !
b10000000 (
b1000 &
b1000 .
b11 )
b11 ,
b111 "
b111 %
b111 $
#90000
b0 !
b0 (
b0 &
b0 .
b1 )
b1 ,
0-
b101 "
b101 %
0#
b1000 $
