240968332 (Backup)/DISL (Backup)/lab6/priority_encoder_4to2.v
module priority_encoder_4to2 (
    input  [3:0] in,
    output reg [1:0] out
);

always @(*) begin
    casex (in)
        4'b1xxx: out = 2'b11;  // Highest priority input is bit 3
        4'b01xx: out = 2'b10;  // Next priority bit 2
        4'b001x: out = 2'b01;  // Next priority bit 1
        4'b0001: out = 2'b00;  // Lowest priority bit 0
        default: out = 2'bxx;  // No inputs active
    endcase
end

endmodule

240968332 (Backup)/DISL (Backup)/lab6/tb_priority_encoder_4to2.v
`timescale 1ns / 1ps

module tb_priority_encoder_4to2;

    reg [3:0] in;
    wire [1:0] out;

    // Instantiate the priority encoder
    priority_encoder_4to2 uut (
        .in(in),
        .out(out)
    );

    initial begin
        $dumpfile("priority_encoder_4to2_tb.vcd");
        $dumpvars(0, tb_priority_encoder_4to2);

        $display("Time\t in     | out");
        $display("---------------------");

        in = 4'b0000; #10 $display("%0t\t %b | %b", $time, in, out);
        in = 4'b0001; #10 $display("%0t\t %b | %b", $time, in, out);
        in = 4'b0010; #10 $display("%0t\t %b | %b", $time, in, out);
        in = 4'b0100; #10 $display("%0t\t %b | %b", $time, in, out);
        in = 4'b1000; #10 $display("%0t\t %b | %b", $time, in, out);
        in = 4'b1010; #10 $display("%0t\t %b | %b", $time, in, out);
        in = 4'b0110; #10 $display("%0t\t %b | %b", $time, in, out);
        in = 4'b1111; #10 $display("%0t\t %b | %b", $time, in, out);

        $finish;
    end

endmodule

240968332 (Backup)/DISL (Backup)/lab6/priority_encoder_4to2_tb.vcd
$date
	Thu Sep 11 15:27:53 2025
$end
$version
	Icarus Verilog
$end
$timescale
	1ps
$end
$scope module tb_priority_encoder_4to2 $end
$var wire 2 ! out [1:0] $end
$var reg 4 " in [3:0] $end
$scope module uut $end
$var wire 4 # in [3:0] $end
$var reg 2 $ out [1:0] $end
$upscope $end
$upscope $end
$enddefinitions $end
#0
$dumpvars
bx $
b0 #
b0 "
bx !
$end
#10000
b0 !
b0 $
b1 "
b1 #
#20000
b1 !
b1 $
b10 "
b10 #
#30000
b10 !
b10 $
b100 "
b100 #
#40000
b11 !
b11 $
b1000 "
b1000 #
#50000
b1010 "
b1010 #
#60000
b10 !
b10 $
b110 "
b110 #
#70000
b11 !
b11 $
b1111 "
b1111 #
