240968332 (Backup)/DISL (Backup)/lab9/jk_seq.v
module jk_seq(
    input wire clk,
    input wire E,
    input wire x,
    output reg A,
    output reg B
);

wire J_A, K_A, J_B, K_B;

assign J_A = E & (~x & ~B | x & B);
assign K_A = J_A;

assign J_B = E;
assign K_B = E;

initial begin
	A=0;
	B=0;
end

always @(posedge clk) begin
    case ({J_A, K_A, A})
        3'b000, 3'b001: A <= A;
        3'b010, 3'b011: A <= 0;
        3'b100, 3'b101: A <= 1;
        3'b110, 3'b111: A <= ~A;
        default: A <= A;
    endcase

    case ({J_B, K_B, B})
        3'b000, 3'b001: B <= B;
        3'b010, 3'b011: B <= 0;
        3'b100, 3'b101: B <= 1;
        3'b110, 3'b111: B <= ~B;
        default: B <= B;
    endcase
end
endmodule

240968332 (Backup)/DISL (Backup)/lab9/jk_seq_tb.v
`timescale 1ns/1ns
`include "jk_seq.v"

module jk_seq_tb();

reg clk;
reg E;
reg x;
wire A, B;

jk_seq dut (
    .clk(clk),
    .E(E),
    .x(x),
    .A(A),
    .B(B)
);

initial clk = 0;
always #10 clk = ~clk;

initial begin

    $dumpfile("jk_seq_tb.vcd");
    $dumpvars(0, jk_seq_tb);

    E = 0;
    x = 0;

    #10;

    E = 0; x = 0;
    #40;

    E = 1; x = 1;
    #80;

    E = 1; x = 0;
    #80;

    E = 0;
    #40;

    $display("Test complete");
    $stop;
end
endmodule

240968332 (Backup)/DISL (Backup)/lab9/jk_seq_tb.vcd
$date
	Fri Oct 10 11:50:18 2025
$end
$version
	Icarus Verilog
$end
$timescale
	1ns
$end
$scope module jk_seq_tb $end
$var wire 1 ! B $end
$var wire 1 " A $end
$var reg 1 # E $end
$var reg 1 $ clk $end
$var reg 1 % x $end
$scope module dut $end
$var wire 1 # E $end
$var wire 1 & J_A $end
$var wire 1 ' J_B $end
$var wire 1 ( K_A $end
$var wire 1 ) K_B $end
$var wire 1 $ clk $end
$var wire 1 % x $end
$var reg 1 " A $end
$var reg 1 ! B $end
$upscope $end
$upscope $end
$enddefinitions $end
#0
$dumpvars
0)
0(
0'
0&
0%
0$
0#
0"
0!
$end
#10
1$
#20
0$
#30
1$
#40
0$
#50
1!
1"
1(
1&
1$
1%
1'
1)
1#
#60
0$
#70
0(
0&
0!
0"
1$
#80
0$
#90
1(
1&
1!
1$
#100
0$
#110
0(
0&
0!
1"
1$
#120
0$
#130
1!
0(
0&
1$
0%
#140
0$
#150
1(
1&
0!
1$
#160
0$
#170
0(
0&
1!
0"
1$
#180
0$
#190
1(
1&
0!
1$
#200
0$
#210
0(
0&
1$
0'
0)
0#
