240968332 (Backup)/DISL (Backup)/lab9/sequential_circuit.v
module sequential_circuit(
    input clk,
    input x,
    output A,
    output B
);

    wire T_A, T_B;
    wire A_wire, B_wire;

    assign A = A_wire;
    assign B = B_wire;

    assign T_A = (~x & B_wire) | (~A_wire & B_wire);
    assign T_B = (x & ~A_wire & B_wire) | (~x & A_wire) | (~x & ~B_wire);

    T_FF ff_A(
        .clk(clk),
        .T(T_A),
        .Q(A_wire)
    );

    T_FF ff_B(
        .clk(clk),
        .T(T_B),
        .Q(B_wire)
    );

endmodule

module T_FF(
    input clk,
    input T,
    output reg Q
);
    initial Q=0;
    always @(posedge clk) begin
        Q <= Q ^ T;
    end
endmodule

240968332 (Backup)/DISL (Backup)/lab9/sequential_circuit_tb.v
`timescale 1ns/1ns
`include "sequential_circuit.v"

module sequential_circuit_tb;

reg clk;
reg x;
wire A;
wire B;

sequential_circuit uut(
    .clk(clk),
    .x(x),
    .A(A),
    .B(B)
);

initial begin
    $dumpfile("sequential_circuit.vcd");
    $dumpvars(0, sequential_circuit_tb);
end

initial begin
    clk = 0;
    forever #10 clk = ~clk;
end

initial begin
    x = 0;
    #20 x = 1;
    #30 x = 0;
    #40 x = 1;
    #50 x = 0;
    #60 
    $display("Test Complete");
    $stop;
    
end
endmodule

240968332 (Backup)/DISL (Backup)/lab9/sequential_circuit.vcd
$date
	Fri Oct 10 12:28:31 2025
$end
$version
	Icarus Verilog
$end
$timescale
	1ns
$end
$scope module sequential_circuit_tb $end
$var wire 1 ! B $end
$var wire 1 " A $end
$var reg 1 # clk $end
$var reg 1 $ x $end
$scope module uut $end
$var wire 1 " A $end
$var wire 1 ! B $end
$var wire 1 % T_A $end
$var wire 1 & T_B $end
$var wire 1 # clk $end
$var wire 1 $ x $end
$var wire 1 ' B_wire $end
$var wire 1 ( A_wire $end
$scope module ff_A $end
$var wire 1 % T $end
$var wire 1 # clk $end
$var reg 1 ( Q $end
$upscope $end
$scope module ff_B $end
$var wire 1 & T $end
$var wire 1 # clk $end
$var reg 1 ' Q $end
$upscope $end
$upscope $end
$upscope $end
$enddefinitions $end
#0
$dumpvars
0(
0'
1&
0%
0$
0#
0"
0!
$end
#10
0&
1%
1!
1'
1#
#20
1&
0#
1$
#30
0&
0%
0!
0'
1"
1(
1#
#40
0#
#50
1&
1#
0$
#60
0#
#70
1%
1!
1'
1#
#80
0#
#90
0"
0(
0!
0'
0&
0%
1#
1$
#100
0#
#110
1#
#120
0#
#130
1#
#140
1&
0#
0$
#150
0&
1%
1!
1'
1#
#160
0#
#170
1&
1"
1(
1#
#180
0#
#190
0%
0!
0'
0"
0(
1#
