240968332 (Backup)/DISL (Backup)/lab3/four.v
module four(a,b,c,d,f);
	input a,b,c,d;
	output f;
	wire f1,f2,f3;
	assign f1 = ~(b&(~(c&c)));
	assign f2 = ~(a&b);
	assign f3 = ~(d&a);
	assign f = ~((~(f1&f2&f3))&(~(f1&f2&f3)));
endmodule

240968332 (Backup)/DISL (Backup)/lab2/four_tb.v
`timescale 1ns/1ns
`include "four.v"

module four_tb();
    reg a, b, c, d;
    wire f;
    four ques1(a, b, c, d, f);

    initial begin
        $dumpfile("four.vcd");
        $dumpvars(0, four_tb);

        a=1'b0; b=1'b0; c=1'b0; d=1'b0; #20;
        a=1'b0; b=1'b0; c=1'b0; d=1'b1; #20;
        a=1'b0; b=1'b0; c=1'b1; d=1'b0; #20;
        a=1'b0; b=1'b0; c=1'b1; d=1'b1; #20;
        a=1'b0; b=1'b1; c=1'b0; d=1'b0; #20;
        a=1'b0; b=1'b1; c=1'b0; d=1'b1; #20;
        a=1'b0; b=1'b1; c=1'b1; d=1'b0; #20;
        a=1'b0; b=1'b1; c=1'b1; d=1'b1; #20;
        a=1'b1; b=1'b0; c=1'b0; d=1'b0; #20;
        a=1'b1; b=1'b0; c=1'b0; d=1'b1; #20;
        a=1'b1; b=1'b0; c=1'b1; d=1'b0; #20;
        a=1'b1; b=1'b0; c=1'b1; d=1'b1; #20;
        a=1'b1; b=1'b1; c=1'b0; d=1'b0; #20;
        a=1'b1; b=1'b1; c=1'b0; d=1'b1; #20;
        a=1'b1; b=1'b1; c=1'b1; d=1'b0; #20;
        a=1'b1; b=1'b1; c=1'b1; d=1'b1; #20;

        $display("Test complete");
        $finish;
    end
endmodule

240968332 (Backup)/DISL (Backup)/lab3/four.vcd
$date
	Thu Aug 14 16:01:28 2025
$end
$version
	Icarus Verilog
$end
$timescale
	1ns
$end
$scope module four_tb $end
$var wire 1 ! f $end
$var reg 1 " a $end
$var reg 1 # b $end
$var reg 1 $ c $end
$var reg 1 % d $end
$scope module ques1 $end
$var wire 1 " a $end
$var wire 1 # b $end
$var wire 1 $ c $end
$var wire 1 % d $end
$var wire 1 ! f $end
$var wire 1 & f1 $end
$var wire 1 ' f2 $end
$var wire 1 ( f3 $end
$upscope $end
$upscope $end
$enddefinitions $end
#0
$dumpvars
1(
1'
1&
0%
0$
0#
0"
1!
$end
#20
1%
#40
0%
1$
#60
1%
#80
0!
0&
0%
0$
1#
#100
1%
#120
1!
1&
0%
1$
#140
1%
#160
0%
0$
0#
1"
#180
0!
0(
1%
#200
1!
1(
0%
1$
#220
0!
0(
1%
#240
0&
1(
0'
0%
0$
1#
#260
0(
1%
#280
1&
1(
0%
1$
#300
0(
1%
