240968332 (Backup)/DISL (Backup)/lab3/one.v
module one(a,b,c,d,f);
	input a,b,c,d;
	output f;
	wire f1,f2;
	assign f1 = (~(~(b&b)&a));
	assign f2 = (~(~(d&d)&c));
	assign f = (~(f1&f2));
endmodule

240968332 (Backup)/DISL (Backup)/lab3/one_tb.v
`timescale 1ns/1ns
`include "one.v"

module one_tb();
    reg a, b, c, d;
    wire f;
    one ques1(a, b, c, d, f);

    initial begin
        $dumpfile("one.vcd");
        $dumpvars(0, one_tb);

        a=1'b0; b=1'b0; c=1'b0; d=1'b0; #20;
        a=1'b0; b=1'b0; c=1'b0; d=1'b1; #20;
        a=1'b0; b=1'b0; c=1'b1; d=1'b0; #20;
        a=1'b0; b=1'b0; c=1'b1; d=1'b1; #20;
        a=1'b0; b=1'b1; c=1'b0; d=1'b0; #20;
        a=1'b0; b=1'b1; c=1'b0; d=1'b1; #20;
        a=1'b0; b=1'b1; c=1'b1; d=1'b0; #20;
        a=1'b0; b=1'b1; c=1'b1; d=1'b1; #20;
        a=1'b1; b=1'b0; c=1'b0; d=1'b0; #20;
        a=1'b1; b=1'b0; c=1'b0; d=1'b1; #20;
        a=1'b1; b=1'b0; c=1'b1; d=1'b0; #20;
        a=1'b1; b=1'b0; c=1'b1; d=1'b1; #20;
        a=1'b1; b=1'b1; c=1'b0; d=1'b0; #20;
        a=1'b1; b=1'b1; c=1'b0; d=1'b1; #20;
        a=1'b1; b=1'b1; c=1'b1; d=1'b0; #20;
        a=1'b1; b=1'b1; c=1'b1; d=1'b1; #20;

        $display("Test complete");
        $finish;
    end
endmodule

240968332 (Backup)/DISL (Backup)/lab3/one.vcd
$date
	Thu Aug 14 14:58:38 2025
$end
$version
	Icarus Verilog
$end
$timescale
	1ns
$end
$scope module one_tb $end
$var wire 1 ! f $end
$var reg 1 " a $end
$var reg 1 # b $end
$var reg 1 $ c $end
$var reg 1 % d $end
$scope module ques1 $end
$var wire 1 " a $end
$var wire 1 # b $end
$var wire 1 $ c $end
$var wire 1 % d $end
$var wire 1 ! f $end
$var wire 1 & f1 $end
$var wire 1 ' f2 $end
$upscope $end
$upscope $end
$enddefinitions $end
#0
$dumpvars
1'
1&
0%
0$
0#
0"
0!
$end
#20
1%
#40
1!
0'
0%
1$
#60
0!
1'
1%
#80
0%
0$
1#
#100
1%
#120
1!
0'
0%
1$
#140
0!
1'
1%
#160
1!
0&
0%
0$
0#
1"
#180
1%
#200
0'
0%
1$
#220
1'
1%
#240
0!
1&
0%
0$
1#
#260
1%
#280
1!
0'
0%
1$
#300
0!
1'
1%
