240968332 (Backup)/DISL (Backup)/lab3/three.v
module three(a,b,c,d,f);
	input a,b,c,d;
	output f;
	wire f1,f2;
	assign f1 = ~(c|(~(d|d)));
	assign f2 = ~(a|(~(d|d)));
	assign f = ~((~(f1|f2))|(~(f1|f2)));
endmodule

240968332 (Backup)/DISL (Backup)/lab2/three_tb.v
`timescale 1ns/1ns
`include "three.v"

module three_tb();
    reg a, b, c, d;
    wire f;
    three ques1(a, b, c, d, f);

    initial begin
        $dumpfile("three.vcd");
        $dumpvars(0, three_tb);

        a=1'b0; b=1'b0; c=1'b0; d=1'b0; #20;
        a=1'b0; b=1'b0; c=1'b0; d=1'b1; #20;
        a=1'b0; b=1'b0; c=1'b1; d=1'b0; #20;
        a=1'b0; b=1'b0; c=1'b1; d=1'b1; #20;
        a=1'b0; b=1'b1; c=1'b0; d=1'b0; #20;
        a=1'b0; b=1'b1; c=1'b0; d=1'b1; #20;
        a=1'b0; b=1'b1; c=1'b1; d=1'b0; #20;
        a=1'b0; b=1'b1; c=1'b1; d=1'b1; #20;
        a=1'b1; b=1'b0; c=1'b0; d=1'b0; #20;
        a=1'b1; b=1'b0; c=1'b0; d=1'b1; #20;
        a=1'b1; b=1'b0; c=1'b1; d=1'b0; #20;
        a=1'b1; b=1'b0; c=1'b1; d=1'b1; #20;
        a=1'b1; b=1'b1; c=1'b0; d=1'b0; #20;
        a=1'b1; b=1'b1; c=1'b0; d=1'b1; #20;
        a=1'b1; b=1'b1; c=1'b1; d=1'b0; #20;
        a=1'b1; b=1'b1; c=1'b1; d=1'b1; #20;

        $display("Test complete");
        $finish;
    end
endmodule

240968332 (Backup)/DISL (Backup)/lab3/three.vcd
$date
	Thu Aug 14 15:54:37 2025
$end
$version
	Icarus Verilog
$end
$timescale
	1ns
$end
$scope module three_tb $end
$var wire 1 ! f $end
$var reg 1 " a $end
$var reg 1 # b $end
$var reg 1 $ c $end
$var reg 1 % d $end
$scope module ques1 $end
$var wire 1 " a $end
$var wire 1 # b $end
$var wire 1 $ c $end
$var wire 1 % d $end
$var wire 1 ! f $end
$var wire 1 & f1 $end
$var wire 1 ' f2 $end
$upscope $end
$upscope $end
$enddefinitions $end
#0
$dumpvars
0'
0&
0%
0$
0#
0"
0!
$end
#20
1!
1&
1'
1%
#40
0!
0'
0&
0%
1$
#60
1!
1'
1%
#80
0!
0'
0&
0%
0$
1#
#100
1!
1&
1'
1%
#120
0!
0'
0&
0%
1$
#140
1!
1'
1%
#160
0!
0&
0'
0%
0$
0#
1"
#180
1!
1&
1%
#200
0!
0&
0%
1$
#220
1%
#240
0!
0&
0%
0$
1#
#260
1!
1&
1%
#280
0!
0&
0%
1$
#300
1%
