240968332 (Backup)/DISL (Backup)/lab3/two.v
module two(a,b,c,d,f);
	input a,b,c,d;
	output f;
	wire f1,f2,f3;
	assign f1 = ~(b|c);
	assign f2 = ~(a|c|~(d|d));
	assign f3 = ~(b|d);
	assign f = ~((~(f1|f2|f3))|~(f1|f2|f3));
endmodule

240968332 (Backup)/DISL (Backup)/lab3/two_tb.v
`timescale 1ns/1ns
`include "two.v"

module two_tb();
    reg a, b, c, d;
    wire f;
    two ques1(a, b, c, d, f);

    initial begin
        $dumpfile("two.vcd");
        $dumpvars(0, two_tb);

        a=1'b0; b=1'b0; c=1'b0; d=1'b0; #20;
        a=1'b0; b=1'b0; c=1'b0; d=1'b1; #20;
        a=1'b0; b=1'b0; c=1'b1; d=1'b0; #20;
        a=1'b0; b=1'b0; c=1'b1; d=1'b1; #20;
        a=1'b0; b=1'b1; c=1'b0; d=1'b0; #20;
        a=1'b0; b=1'b1; c=1'b0; d=1'b1; #20;
        a=1'b0; b=1'b1; c=1'b1; d=1'b0; #20;
        a=1'b0; b=1'b1; c=1'b1; d=1'b1; #20;
        a=1'b1; b=1'b0; c=1'b0; d=1'b0; #20;
        a=1'b1; b=1'b0; c=1'b0; d=1'b1; #20;
        a=1'b1; b=1'b0; c=1'b1; d=1'b0; #20;
        a=1'b1; b=1'b0; c=1'b1; d=1'b1; #20;
        a=1'b1; b=1'b1; c=1'b0; d=1'b0; #20;
        a=1'b1; b=1'b1; c=1'b0; d=1'b1; #20;
        a=1'b1; b=1'b1; c=1'b1; d=1'b0; #20;
        a=1'b1; b=1'b1; c=1'b1; d=1'b1; #20;

        $display("Test complete");
        $finish;
    end
endmodule

240968332 (Backup)/DISL (Backup)/lab3/two.vcd
$date
	Thu Aug 14 15:36:29 2025
$end
$version
	Icarus Verilog
$end
$timescale
	1ns
$end
$scope module two_tb $end
$var wire 1 ! f $end
$var reg 1 " a $end
$var reg 1 # b $end
$var reg 1 $ c $end
$var reg 1 % d $end
$scope module ques1 $end
$var wire 1 " a $end
$var wire 1 # b $end
$var wire 1 $ c $end
$var wire 1 % d $end
$var wire 1 ! f $end
$var wire 1 & f1 $end
$var wire 1 ' f2 $end
$var wire 1 ( f3 $end
$upscope $end
$upscope $end
$enddefinitions $end
#0
$dumpvars
1(
0'
1&
0%
0$
0#
0"
1!
$end
#20
1'
0(
1%
#40
0'
1(
0&
0%
1$
#60
0!
0(
1%
#80
0!
0'
0%
0$
1#
#100
1!
1'
1%
#120
0!
0'
0%
1$
#140
1%
#160
1!
1&
1(
0%
0$
0#
1"
#180
0(
1%
#200
1(
0&
0%
1$
#220
0!
0(
1%
#240
0%
0$
1#
#260
1%
#280
0%
1$
#300
1%
