240968332 (Backup)/DISL (Backup)/lab8/register_nbit.v
module register_nbit #(
    parameter N = 4  // You can change this to any desired bit-width
)(
    input wire clk,
    input wire rst,
    input wire en,
    input wire [N-1:0] d,
    output wire [N-1:0] q
);
    reg [N-1:0] q_reg;

    always @(posedge clk) begin
        if (rst)
            q_reg <= {N{1'b0}};  // Reset all bits to 0
        else if (en)
            q_reg <= d;          // Load input vector
    end

    assign q = q_reg;
endmodule

240968332 (Backup)/DISL (Backup)/lab8/register_nbit_tb.v
`timescale 1ns / 1ps

module register_nbit_tb;
    // Parameters
    parameter N = 4;

    // Testbench signals
    reg clk;
    reg rst;
    reg en;
    reg [N-1:0] d;
    wire [N-1:0] q;

    // Instantiate the register
    register_nbit #(.N(N)) uut (
        .clk(clk),
        .rst(rst),
        .en(en),
        .d(d),
        .q(q)
    );

    // Clock generation: 10ns period
    initial clk = 0;
    always #5 clk = ~clk;

    // VCD dump for waveform viewing
    initial begin
        $dumpfile("register_nbit_tb.vcd");
        $dumpvars(0, register_nbit_tb);
    end

    // Test sequence
    initial begin
        $display("Time\tRST\tEN\tD\tQ");
        $monitor("%g\t%b\t%b\t%h\t%h", $time, rst, en, d, q);

        // Case 1: Reset active
        rst = 1; en = 0; d = 4'b0000;
        #10;

        // Case 2: Load 1010 with enable
        rst = 0; en = 1; d = 4'b1010;
        #10;

        // Case 3: Hold value (enable low)
        en = 0; d = 4'b1111;
        #10;

        // Case 4: Load 0101
        en = 1; d = 4'b0101;
        #10;

        // Case 5: Reset again
        rst = 1;
        #10;

        // Case 6: Load 1100 after reset
        rst = 0; en = 1; d = 4'b1100;
        #10;

        $finish;
    end
endmodule

240968332 (Backup)/DISL (Backup)/lab8/register_nbit_tb.vcd
$date
	Thu Oct 16 15:12:05 2025
$end
$version
	Icarus Verilog
$end
$timescale
	1ps
$end
$scope module register_nbit_tb $end
$var wire 4 ! q [3:0] $end
$var reg 1 " clk $end
$var reg 4 # d [3:0] $end
$var reg 1 $ en $end
$var reg 1 % rst $end
$scope module uut $end
$var wire 1 " clk $end
$var wire 4 & d [3:0] $end
$var wire 1 $ en $end
$var wire 4 ' q [3:0] $end
$var wire 1 % rst $end
$var reg 4 ( q_reg [3:0] $end
$upscope $end
$upscope $end
$enddefinitions $end
#0
$dumpvars
bx (
bx '
b0 &
1%
0$
b0 #
0"
bx !
$end
#5000
b0 !
b0 '
b0 (
1"
#10000
0"
b1010 #
b1010 &
1$
0%
#15000
b1010 !
b1010 '
b1010 (
1"
#20000
0"
b1111 #
b1111 &
0$
#25000
1"
#30000
0"
b101 #
b101 &
1$
#35000
b101 !
b101 '
b101 (
1"
#40000
0"
1%
#45000
b0 !
b0 '
b0 (
1"
#50000
0"
b1100 #
b1100 &
0%
#55000
b1100 !
b1100 '
b1100 (
1"
