240968332 (Backup)/DISL (Backup)/lab1/q1.v
module q1(a,b,c,d,f);
	input a,b,c,d;
	wire p,q,r,s,t,u,v;
	output f;
	and(p,a,b);
	or(q,p,c);
	not(r,q);
	and(s,r,d);
	and(t,a,b);
	or(u,t,c);
	or(v,u,d);
	and(f,s,v);
endmodule

240968332 (Backup)/DISL (Backup)/lab1/q1_tb.v
`timescale 1ns/1ns
`include "q1.v"

module q1_tb();
    reg a, b, c, d;
    wire f;
    q1 ques1(a, b, c, d, f);

    initial begin
        $dumpfile("q1.vcd");
        $dumpvars(0, q1_tb);

        a=1'b1; b=1'b0; c=1'b0; d=1'b0; #20;
        a=1'b0; b=1'b0; c=1'b0; d=1'b1; #20;
        a=1'b0; b=1'b0; c=1'b1; d=1'b0; #20;
        a=1'b0; b=1'b0; c=1'b1; d=1'b1; #20;
        a=1'b0; b=1'b1; c=1'b0; d=1'b0; #20;
        a=1'b0; b=1'b1; c=1'b0; d=1'b1; #20;
        a=1'b0; b=1'b1; c=1'b1; d=1'b0; #20;
        a=1'b0; b=1'b1; c=1'b1; d=1'b1; #20;
        a=1'b1; b=1'b0; c=1'b0; d=1'b0; #20;
        a=1'b1; b=1'b0; c=1'b0; d=1'b1; #20;
        a=1'b1; b=1'b0; c=1'b1; d=1'b0; #20;
        a=1'b1; b=1'b0; c=1'b1; d=1'b1; #20;
        a=1'b1; b=1'b1; c=1'b0; d=1'b0; #20;
        a=1'b1; b=1'b1; c=1'b0; d=1'b1; #20;
        a=1'b1; b=1'b1; c=1'b1; d=1'b0; #20;
        a=1'b1; b=1'b1; c=1'b1; d=1'b1; #20;

        $display("Test complete");
        $finish;
    end
endmodule

240968332 (Backup)/DISL (Backup)/lab1/q1.vcd
$date
	Thu Jul 31 15:17:13 2025
$end
$version
	Icarus Verilog
$end
$timescale
	1ns
$end
$scope module q1_tb $end
$var wire 1 ! f $end
$var reg 1 " a $end
$var reg 1 # b $end
$var reg 1 $ c $end
$var reg 1 % d $end
$scope module ques1 $end
$var wire 1 " a $end
$var wire 1 # b $end
$var wire 1 $ c $end
$var wire 1 % d $end
$var wire 1 ! f $end
$var wire 1 & p $end
$var wire 1 ' q $end
$var wire 1 ( r $end
$var wire 1 ) s $end
$var wire 1 * t $end
$var wire 1 + u $end
$var wire 1 , v $end
$upscope $end
$upscope $end
$enddefinitions $end
#0
$dumpvars
0,
0+
0*
0)
1(
0'
0&
0%
0$
0#
1"
0!
$end
#20
1!
1)
1,
1%
0"
#40
0!
0(
0)
1'
1+
0%
1$
#60
1%
#80
1(
0,
0'
0+
0%
0$
1#
#100
1!
1)
1,
1%
#120
0!
0(
0)
1'
1+
0%
1$
#140
1%
#160
1(
0,
0'
0+
0%
0$
0#
1"
#180
1!
1)
1,
1%
#200
0!
0(
0)
1'
1+
0%
1$
#220
1%
#240
1&
1*
0%
0$
1#
#260
1%
#280
0%
1$
#300
1%
